[
{"Tweet_ID": 1574954519435149312, "User": "sundarpichai", "Text": "24 years on and we're still feeling lucky:) Grateful to all of you for your support, and we'll keep working hard to\u2026 https://t.co/1R2ESGeMse", "City": "Mountain View", "Country": "United States", "Coordinates": [[[-122.117916, 37.3567709], [-122.044969, 37.3567709], [-122.044969, 37.436935], [-122.117916, 37.436935]]], "Entities": {"hashtags": [], "symbols": [], "user_mentions": [], "urls": [{"url": "https://t.co/1R2ESGeMse", "expanded_url": "https://twitter.com/i/web/status/1574954519435149312", "display_url": "twitter.com/i/web/status/1\u2026", "indices": [117, 140]}]}, "Date": "2022-09-28 02:49:53+00:00"},
{"Tweet_ID": 1525329430406520833, "User": "sundarpichai", "Text": "So much fun to meet @michaeljosh @ijustine @NBTJacklyn after the #GoogleIO keynote this week. Must admit they taugh\u2026 https://t.co/kzxXPjo5Y4", "City": "Mountain View", "Country": "United States", "Coordinates": [[[-122.117916, 37.3567709], [-122.044969, 37.3567709], [-122.044969, 37.436935], [-122.117916, 37.436935]]], "Entities": {"hashtags": [{"text": "GoogleIO", "indices": [65, 74]}], "symbols": [], "user_mentions": [{"screen_name": "michaeljosh", "name": "Michael Josh", "id": 685813, "id_str": "685813", "indices": [20, 32]}, {"screen_name": "ijustine", "name": "iJustine", "id": 7846, "id_str": "7846", "indices": [33, 42]}, {"screen_name": "NBTJacklyn", "name": "Jacklyn", "id": 3054363644, "id_str": "3054363644", "indices": [43, 54]}], "urls": [{"url": "https://t.co/kzxXPjo5Y4", "expanded_url": "https://twitter.com/i/web/status/1525329430406520833", "display_url": "twitter.com/i/web/status/1\u2026", "indices": [117, 140]}]}, "Date": "2022-05-14 04:17:30+00:00"},
{"Tweet_ID": 1524425079148269568, "User": "sundarpichai", "Text": "Nice to be back IRL at Shoreline! See you soon:) #GoogleIO https://t.co/6A3mtEIAl4", "City": "Shoreline Amphitheatre", "Country": "United States", "Coordinates": [[[-122.08065698109668, 37.42605714973578], [-122.08065698109668, 37.42605714973578], [-122.08065698109668, 37.42605714973578], [-122.08065698109668, 37.42605714973578]]], "Entities": {"hashtags": [{"text": "GoogleIO", "indices": [49, 58]}], "symbols": [], "user_mentions": [], "urls": [], "media": [{"id": 1524425065055412224, "id_str": "1524425065055412224", "indices": [59, 82], "media_url": "http://pbs.twimg.com/media/FSfYhRlUYAA5BF2.jpg", "media_url_https": "https://pbs.twimg.com/media/FSfYhRlUYAA5BF2.jpg", "url": "https://t.co/6A3mtEIAl4", "display_url": "pic.twitter.com/6A3mtEIAl4", "expanded_url": "https://twitter.com/sundarpichai/status/1524425079148269568/photo/1", "type": "photo", "sizes": {"thumb": {"w": 150, "h": 150, "resize": "crop"}, "large": {"w": 2048, "h": 1152, "resize": "fit"}, "medium": {"w": 1200, "h": 675, "resize": "fit"}, "small": {"w": 680, "h": 383, "resize": "fit"}}}]}, "Date": "2022-05-11 16:23:55+00:00"}
]
